[
  {
    "id": 1,
    "name": "John Doe",
    "email": "johdoe@example.com",
    "profession": "Software Engineer"
  },
  {
    "id": 2,
    "name": "Jane Smith",
    "email": "janesmith@example.com",
    "profession": "Data Scientist"
  },
  {
    "id": 3,
    "name": "Alice Johnson",
    "email": "alicejohnson@example.com",
    "profession": "Product Manager"
  },
  {
    "id": 4,
    "name": "Bob Brown",
    "email": "bobbrown@example.com",
    "profession": "UX Designer"
  },
  {
    "id": 5,
    "name": "Charlie Davis",
    "email": "charliedavis@example.com",
    "profession": "DevOps Engineer"
  },
  {
    "id": 6,
    "name": "Diana Evans",
    "email": "dianaevans@example.com",
    "profession": "QA Engineer"
  },
  {
    "id": 7,
    "name": "Ethan Harris",
    "email": "ethanharris@example.com",
    "profession": "Backend Developer"
  },
  {
    "id": 8,
    "name": "Fiona Green",
    "email": "fionagreen@example.com",
    "profession": "Frontend Developer"
  },
  {
    "id": 9,
    "name": "George Hill",
    "email": "georgehill@example.com",
    "profession": "System Administrator"
  },
  {
    "id": 10,
    "name": "Hannah King",
    "email": "hannahking@example.com",
    "profession": "Business Analyst"
  },
  {
    "id": 11,
    "name": "Ian Lee",
    "email": "ianlee@example.com",
    "profession": "Scrum Master"
  }
]
